{"cameraMode":{"drawMode":0,"name":"Shaded","section":"Shading Mode"},"sceneLighting":true,"audioPlay":false,"sceneViewState":{"m_AlwaysRefresh":false,"showFog":true,"showSkybox":true,"showFlares":true,"showImageEffects":true,"showParticleSystems":true,"showVisualEffectGraphs":true,"m_FxEnabled":true},"in2DMode":false,"pivot":{"x":-0.6456596851348877,"y":0.4914570450782776,"z":-0.38522565364837649},"rotation":{"x":-0.08026400208473206,"y":0.9131409525871277,"z":-0.21940962970256806,"w":-0.33404576778411868},"size":5.393944263458252,"orthographic":false}