{"cameraMode":{"drawMode":0,"name":"Shaded","section":"Shading Mode"},"sceneLighting":true,"audioPlay":false,"sceneViewState":{"m_AlwaysRefresh":false,"showFog":true,"showSkybox":true,"showFlares":true,"showImageEffects":true,"showParticleSystems":true,"showVisualEffectGraphs":true,"m_FxEnabled":true},"in2DMode":false,"pivot":{"x":14.93377685546875,"y":7.1951141357421879,"z":198.08680725097657},"rotation":{"x":-0.285887211561203,"y":0.6426388025283814,"z":-0.28145888447761538,"w":-0.6527426838874817},"size":104.4557876586914,"orthographic":false}