{"cameraMode":{"drawMode":0,"name":"Shaded","section":"Shading Mode"},"sceneLighting":false,"audioPlay":false,"sceneViewState":{"m_AlwaysRefresh":false,"showFog":true,"showSkybox":false,"showFlares":true,"showImageEffects":true,"showParticleSystems":true,"showVisualEffectGraphs":true,"m_FxEnabled":true},"in2DMode":false,"pivot":{"x":-2.031080722808838,"y":1.6095749139785767,"z":26.778409957885743},"rotation":{"x":-0.2369174063205719,"y":-0.6872134804725647,"z":0.2553822696208954,"w":-0.6375036239624023},"size":7.495438098907471,"orthographic":false}